src/autodocs.py
src/cli.py
src/documenters.py
llm_autodocs-0.0.8.dist-info/METADATA
llm_autodocs-0.0.8.dist-info/WHEEL
llm_autodocs-0.0.8.dist-info/entry_points.txt
llm_autodocs-0.0.8.dist-info/RECORD
